{
   "BRA": "brazil",
      "KHM": "cambodia",
      "COL": "columbia",
      "CRI": "costa rica",
      "DNK": "denmark",
      "DOM": "dominican republic",
      "DEU": "germany",
      "HKG": "hong kong",
      "IND": "india",
      "IRL": "ireland",
      "JAM": "jamaica",
      "MYS": "malaysia",
      "MLT": "malta",
      "MNE": "montenegro",
      "MMR": "myanmar",
      "NZL": "new zealand",
      "PHL": "philippines",
      "PRI": "puerto rico",
      "SGP": "singapore",
      "SVK": "slovakia",
      "ZAF": "south africa",
      "ESP": "spain",
      "CHE": "switzerland",
      "TTO": "trinidad and tobago",
      "GBR": "united kingdom",
      "GRD": "grenada",
      "ZMB": "zambia",
      "WA": "WASHINGTON",
      "ISR": "ISRAEL",
      "WI": "WISCONSIN",
      "WV": "WEST VIRGINIA",
      "HI": "HAWAII",
      "CAN": "CANADA",
      "FL": "FLORIDA",
      "WY": "WYOMING",
      "NH": "NEW HAMPSHIRE",
      "NJ": "NEW JERSEY",
      "NM": "NEW MEXICO",
      "TX": "TEXAS",
      "LA": "LOUISIANA",
      "NC": "NORTH CAROLINA",
      "ND": "NORTH DAKOTA",
      "NE": "NEBRASKA",
      "TN": "TENNESSEE",
      "NY": "NEW YORK",
      "PA": "PENNSYLVANIA",
      "RI": "RHODE ISLAND",
      "NV": "NEVADA",
      "VA": "VIRGINIA",
      "FRA": "FRANCE",
      "CO": "COLORADO",
      "CA": "CALIFORNIA",
      "AL": "ALABAMA",
      "AUS": "AUSTRALIA",
      "AR": "ARKANSAS",
      "VT": "VERMONT",
      "IL": "ILLINOIS",
      "GA": "GEORGIA",
      "IN": "INDIANA",
      "IA": "IOWA",
      "OK": "OKLAHOMA",
      "AZ": "ARIZONA",
      "ID": "IDAHO",
      "CT": "CONNECTICUT",
      "ME": "MAINE",
      "MD": "MARYLAND",
      "MA": "MASSACHUSETTS",
      "OH": "OHIO",
      "UT": "UTAH",
      "MO": "MISSOURI",
      "MN": "MINNESOTA",
      "MI": "MICHIGAN",
      "OR": "OREGON",
      "ITA": "ITALY",
      "KS": "KANSAS",
      "MT": "MONTANA",
      "MS": "MISSISSIPPI",
      "SC": "SOUTH CAROLINA",
      "KY": "KENTUCKY",
      "MEX": "MEXICO",
      "SD": "SOUTH DAKOTA"
}
